local_crontab/__init__.py
local_crontab/cmd_line.py
local_crontab/converter.py
local_crontab-0.3.0.dist-info/LICENSE
local_crontab-0.3.0.dist-info/METADATA
local_crontab-0.3.0.dist-info/WHEEL
local_crontab-0.3.0.dist-info/entry_points.txt
local_crontab-0.3.0.dist-info/top_level.txt
local_crontab-0.3.0.dist-info/RECORD
