Metadata-Version: 2.1
Name: local-crontab
Version: 0.3.0
Summary: Convert local crontabs to UTC crontabs
Home-page: https://github.com/Sonic0/local-crontab
Author: Andrea Salvatori
Author-email: andrea.salvatori92@gmail.com
License: MIT
Keywords: cron,timezone,utc
Platform: UNKNOWN
Classifier: Development Status :: 3 - Alpha
Classifier: Intended Audience :: Developers
Classifier: Intended Audience :: System Administrators
Classifier: License :: OSI Approved :: MIT License
Classifier: Programming Language :: Python :: 3
Classifier: Programming Language :: Python :: 3 :: Only
Classifier: Topic :: Software Development :: Libraries :: Python Modules
Requires-Python: >=3.8
Provides-Extra: test
